{
  "fileName": "sb_state.rs",
  "filePath": "rust/switchboard-v2/src/sb_state.rs",
  "url": "https://github.com/switchboard-xyz/sbv2-solana/blob/master/rust/switchboard-v2/src/sb_state.rs",
  "summary": "The code provided is part of the `sbv2-solana` project and defines a `SbState` struct, which represents the state of the system. This state is stored in an account on the Solana blockchain, and the `#[account(zero_copy(unsafe))]` attribute indicates that the account data is stored in a zero-copy format for performance reasons. The `#[repr(packed)]` attribute ensures that the struct is stored in a compact format without padding.\n\nThe `SbState` struct contains the following fields:\n\n- `authority`: A `Pubkey` representing the account authority permitted to make changes to the account. This ensures that only authorized users can modify the state.\n- `token_mint`: A `Pubkey` representing the token mint used for oracle rewards, aggregator leases, and other reward incentives. This is the source of tokens for various activities within the system.\n- `token_vault`: A `Pubkey` representing the token vault used by the program to receive kickbacks. This account stores tokens received as fees or other incentives.\n- `dao_mint`: A `Pubkey` representing the token mint used by the DAO (Decentralized Autonomous Organization). This mint is responsible for creating tokens used for governance and decision-making within the project.\n- `bump`: A `u8` value representing the PDA (Program Derived Address) bump to derive the pubkey. This is used to create a unique address for the account.\n- `_ebuf`: A reserved buffer of 991 bytes for future information. This ensures that the struct can be extended in the future without breaking compatibility.\n\nThe `impl SbState {}` block is currently empty, but it can be used to add methods and functionality to the `SbState` struct in the future.\n\nIn the larger project, the `SbState` struct is likely used to store and manage the global state of the system, including token mints, vaults, and governance information. This state can be accessed and modified by authorized users through transactions on the Solana blockchain.",
  "questions": "1. **Question:** What is the purpose of the `#[account(zero_copy(unsafe))]` attribute in the `SbState` struct definition?\n\n   **Answer:** The `#[account(zero_copy(unsafe))]` attribute is used to indicate that the `SbState` struct should be deserialized directly from the account data without copying the data, which can improve performance. However, it is marked as `unsafe` because it can lead to undefined behavior if the struct layout does not match the account data.\n\n2. **Question:** What is the role of the `_ebuf` field in the `SbState` struct?\n\n   **Answer:** The `_ebuf` field is a reserved buffer for future information. It is currently an array of 991 bytes, which can be used to store additional data in the future without changing the overall size of the `SbState` struct.\n\n3. **Question:** Why is the `impl SbState {}` block empty, and what could be added to it in the future?\n\n   **Answer:** The `impl SbState {}` block is currently empty because there are no methods or associated functions defined for the `SbState` struct at the moment. In the future, developers could add methods or associated functions to implement specific functionality or behavior related to the `SbState` struct."
}